faster_modisco_lite-2.4.0.dist-info/licenses/LICENSE
modiscolite/__init__.py
modiscolite/affinitymat.py
modiscolite/aggregator.py
modiscolite/bed_writer.py
modiscolite/cli.py
modiscolite/cluster.py
modiscolite/core.py
modiscolite/extract_seqlets.py
modiscolite/fasta_writer.py
modiscolite/gapped_kmer.py
modiscolite/io.py
modiscolite/meme_writer.py
modiscolite/report.py
modiscolite/tfmodisco.py
modiscolite/util.py
faster_modisco_lite-2.4.0.dist-info/METADATA
faster_modisco_lite-2.4.0.dist-info/WHEEL
faster_modisco_lite-2.4.0.dist-info/entry_points.txt
faster_modisco_lite-2.4.0.dist-info/top_level.txt
faster_modisco_lite-2.4.0.dist-info/RECORD
