Metadata-Version: 2.4
Name: faster-modisco-lite
Version: 2.4.0
Summary: Transcription Factor MOtif Discovery from Importance SCOres - lite
Author: Jacob Schreiber
Author-email: Muhammed Hasan Celik <muhammedhasancelik@gmail.com>
License: MIT License
Project-URL: Homepage, https://github.com/MuhammedHasan/tfmodisco-lite
Requires-Python: >=3.7
License-File: LICENSE
Requires-Dist: click
Requires-Dist: numpy>=1.21.5
Requires-Dist: scipy>=1.6.2
Requires-Dist: numba>=0.53.1
Requires-Dist: scikit-learn>=1.0.2
Requires-Dist: leidenalg>=0.8.10
Requires-Dist: igraph>=0.9.11
Requires-Dist: tqdm>=4.38.0
Requires-Dist: pandas>=1.4.3
Requires-Dist: logomaker>=0.8
Requires-Dist: h5py>=3.7.0
Requires-Dist: memelite
Requires-Dist: joblib
Requires-Dist: numba-progress
Provides-Extra: test
Requires-Dist: pytest; extra == "test"
Requires-Dist: pytest-cov; extra == "test"
Dynamic: license-file
